eagr/__init__.py
eagr/client/__init__.py
eagr/client/client_side_middleware.py
eagr/client/client_test_helpers.py
eagr/client/client_tracing.py
eagr/client/client_wrapper.py
eagr/client/stub_generator.py
eagr/flask_bridge/Readme.md
eagr/flask_bridge/__init__.py
eagr/flask_bridge/grpc_to_json.py
eagr/grpc_utils/__init__.py
eagr/grpc_utils/method.py
eagr/grpc_utils/response_translation.py
eagr/protos/__init__.py
eagr/protos/test_service.proto
eagr/protos/test_service_pb2.py
eagr/protos/test_service_pb2_grpc.py
eagr/reflection/__init__.py
eagr/reflection/grpc_reflection_interface.py
eagr/reflection/reflection_descriptor_database.py
eagr/server/__init__.py
eagr/server/base.py
eagr/server/middleware.py
eagr/tests/__init__.py
eagr/tests/client/__init__.py
eagr/tests/client/test_client_test_helpers.py
eagr/tests/client/test_client_wrapper.py
eagr/tests/client/test_stub_generator.py
eagr/tests/grpc_utils/__init__.py
eagr/tests/grpc_utils/test_response_translation.py
eagr/tests/reflection/__init__.py
eagr/tests/reflection/test_grpc_reflection_interface.py
eagr/tests/reflection/test_reflection_descriptor_database.py
eagr/tests/reflection/utils.py
eagr/tests/server/__init__.py
eagr/tests/server/test_imports.py
eagr/tests/server/test_middleware.py
eagr-0.2.2.dist-info/LICENSE
eagr-0.2.2.dist-info/WHEEL
eagr-0.2.2.dist-info/METADATA
eagr-0.2.2.dist-info/RECORD
