Metadata-Version: 2.1
Name: eagr
Version: 0.2.2
Summary: A collection of utilities for making GRPC easier to use in python.
Author: Louis Ades
Author-email: louis.ades@kensho.com
Requires-Python: >=3.6,<4.0
Classifier: Programming Language :: Python :: 3
Classifier: Programming Language :: Python :: 3.6
Classifier: Programming Language :: Python :: 3.7
Classifier: Programming Language :: Python :: 3.8
Classifier: Programming Language :: Python :: 3.9
Requires-Dist: Flask (>=0.12.2)
Requires-Dist: backoff (>=1.6.0,<2.0.0)
Requires-Dist: funcy (>=1.7.2,<2.0.0)
Requires-Dist: grpcio (>=1.25,<2.0)
Requires-Dist: grpcio-opentracing (>=1.1,<2.0)
Requires-Dist: grpcio-reflection (>=1.25,<2.0)
Requires-Dist: grpcio-tools (>=1.25,<2.0)
Requires-Dist: opentracing (>=2.2,<3.0)
Requires-Dist: opentracing_instrumentation (>=3.2,<4.0)
Requires-Dist: prometheus_client (>=0.7.1,<0.8.0)
Requires-Dist: protobuf (>=3.6.0,<3.14.0)
Requires-Dist: pytz (>=2019.3,<2020.0)
